aig/__init__.py
aig/demo/client/ollama_client.py
aig/demo/server/Pipfile
aig/demo/server/math_server.py
aig/demo/server/package-lock.json
pylexfluent_agent_interop_gedaia-0.0.3.dist-info/METADATA
pylexfluent_agent_interop_gedaia-0.0.3.dist-info/WHEEL
pylexfluent_agent_interop_gedaia-0.0.3.dist-info/licenses/LICENSE
pylexfluent_agent_interop_gedaia-0.0.3.dist-info/RECORD
